webing/__init__.py
webing/clitools/__init__.py
webing/clitools/cli.py
webing-0.0.0.3.dist-info/METADATA
webing-0.0.0.3.dist-info/WHEEL
webing-0.0.0.3.dist-info/entry_points.txt
webing-0.0.0.3.dist-info/top_level.txt
webing-0.0.0.3.dist-info/RECORD
