Metadata-Version: 2.1
Name: webing
Version: 0.0.0.3
Summary: A very quick way to build a simple backend, help you test your idea conveniently
Home-page: https://gitee.com/peiiii/webing
Author: Wang Pei
Author-email: 1535376447@qq.com
License: UNKNOWN
Platform: UNKNOWN
Classifier: Programming Language :: Python :: 3
Classifier: License :: OSI Approved :: MIT License
Classifier: Operating System :: OS Independent
Requires-Python: >=3.5
Requires-Dist: sanic
Requires-Dist: fire
